{
  "firefox": {
    "version": "103.0.2",
    "url": "https://download-installer.cdn.mozilla.net/pub/firefox/releases/103.0.2/mac/en-US/Firefox%20103.0.2.dmg",
    "sha256": "c3e9e2ec300d231ee6e9cdfe1dd8fc03d62ac6c23d8ddfcc9358e430dca73ea4"
  },
  "firefox-beta": {
    "version": "104.0b9",
    "url": "https://download-installer.cdn.mozilla.net/pub/firefox/releases/104.0b9/mac/en-US/Firefox%20104.0b9.dmg",
    "sha256": "b5a112cba4cf359e8db65bc78e77eb078f596c6c5498f2cff85687ce3a0e6788"
  },
  "firefox-devedition": {
    "version": "104.0b9",
    "url": "https://download-installer.cdn.mozilla.net/pub/devedition/releases/104.0b9/mac/en-US/Firefox%20104.0b9.dmg",
    "sha256": "1f38d80267aef79046f9006cf72e084afce4936d054058e1813c22e6d68271b1"
  },
  "firefox-esr": {
    "version": "91.12.0esr",
    "url": "https://download-installer.cdn.mozilla.net/pub/firefox/releases/91.12.0esr/mac/en-US/Firefox%2091.12.0esr.dmg",
    "sha256": "a925bbc7cf6b276d39b0e7f102b468d1468d301e04d5fb4327927ba10188908f"
  }
}
