{
  "firefox": {
    "version": "105.0.3",
    "url": "https://download-installer.cdn.mozilla.net/pub/firefox/releases/105.0.3/mac/en-US/Firefox%20105.0.3.dmg",
    "sha256": "a0e98a7326e4a518173a5c6703f6e0671027a3471b9c6470b07d4160dfb1059a"
  },
  "firefox-beta": {
    "version": "106.0b9",
    "url": "https://download-installer.cdn.mozilla.net/pub/firefox/releases/106.0b9/mac/en-US/Firefox%20106.0b9.dmg",
    "sha256": "e90a32f9796ead9104e916ccfe2edbe5ac92dcda5392c1e9f1e1453f37a56766"
  },
  "firefox-devedition": {
    "version": "106.0b9",
    "url": "https://download-installer.cdn.mozilla.net/pub/devedition/releases/106.0b9/mac/en-US/Firefox%20106.0b9.dmg",
    "sha256": "b9d0d0a2ec862cf3dac816cb8f081df804db75c9d79060e9fc9f3c7cc0230bf2"
  },
  "firefox-esr": {
    "version": "102.3.0esr",
    "url": "https://download-installer.cdn.mozilla.net/pub/firefox/releases/102.3.0esr/mac/en-US/Firefox%20102.3.0esr.dmg",
    "sha256": "1bae4bd67a915af2f65ee9032df4a225741e5c3360ac5a89cf65fc988d29c420"
  }
}
